.pep8
MANIFEST.in
README.rst
setup.cfg
setup.py
rueckenwind.egg-info/PKG-INFO
rueckenwind.egg-info/SOURCES.txt
rueckenwind.egg-info/dependency_links.txt
rueckenwind.egg-info/entry_points.txt
rueckenwind.egg-info/requires.txt
rueckenwind.egg-info/top_level.txt
rw/__init__.py
rw/cfg.py
rw/cli.py
rw/debugger.py
rw/debugger_protocol.py
rw/event.py
rw/gen.py
rw/htt2.py
rw/http.py
rw/httpbase.py
rw/plugin.py
rw/routing.py
rw/scope.py
rw/server.py
rw/static.py
rw/template.py
rw/testing.py
rw/websocket.py
test/__init__.py
test/common.py
test/scope_py3.py
test/test_cfg.py
test/test_cli.py
test/test_event.py
test/test_example.py
test/test_http.py
test/test_httpbase.py
test/test_plugin.py
test/test_routing.py
test/test_scope.py
test/test_static.py
test/configs/no_rwdb.yml
test/configs/simple.yml
test/example/__init__.py
test/example/test.example.yml
test/example/static/test.example/hello_world.txt
test/example/static/test.example/overwrite.txt
test/example/static2/test.example/hallo_welt.txt
test/example/static2/test.example/overwrite.txt
test/example/templates/test.example/index.html
test/example/templates/test.example/static_files.html
test/example/templates/test.example/sub.html