Metadata-Version: 1.1
Name: rueckenwind
Version: 0.5.3
Summary: tornado based webframework
Home-page: https://github.com/FlorianLudwig/rueckenwind
Author: Florian Ludwig
Author-email: vierzigundzwei@gmail.com
License: http://www.apache.org/licenses/LICENSE-2.0
Platform: UNKNOWN
Classifier: Intended Audience :: Developers
Classifier: License :: OSI Approved :: Apache Software License
Classifier: Programming Language :: Python :: 2.7
Classifier: Programming Language :: Python :: 3
Classifier: Programming Language :: Python :: 3.5
Classifier: Programming Language :: Python :: 3.6
Classifier: Programming Language :: Python :: Implementation :: CPython
Classifier: Programming Language :: Python :: Implementation :: PyPy
